arazzo_generator-0.2.1.dist-info/METADATA
arazzo_generator-0.2.1.dist-info/WHEEL
arazzo_generator-0.2.1.dist-info/entry_points.txt
arazzo_generator-0.2.1.dist-info/licenses/LICENSE
arazzo_generator-0.2.1.dist-info/licenses/NOTICE
arazzo_generator/__init__.py
arazzo_generator/__main__.py
arazzo_generator/analyzers/__init__.py
arazzo_generator/analyzers/base_analyzer.py
arazzo_generator/analyzers/llm_analyzer.py
arazzo_generator/analyzers/workflow_analysis_manager.py
arazzo_generator/api/__init__.py
arazzo_generator/api/app.py
arazzo_generator/api/run.py
arazzo_generator/batch/README.md
arazzo_generator/batch/__init__.py
arazzo_generator/batch/batch_generator.py
arazzo_generator/batch/utils.py
arazzo_generator/cli/__init__.py
arazzo_generator/cli/main.py
arazzo_generator/cli/run.py
arazzo_generator/generator/__init__.py
arazzo_generator/generator/arazzo_generator.py
arazzo_generator/generator/components.py
arazzo_generator/generator/generator_service.py
arazzo_generator/generator/output_mapping_validator.py
arazzo_generator/generator/reference_validator.py
arazzo_generator/generator/workflow_builder.py
arazzo_generator/llm/__init__.py
arazzo_generator/llm/direct_arazzo_generator.py
arazzo_generator/llm/litellm_service.py
arazzo_generator/llm/prompts/direct_llm_arazzo_generation.prompt
arazzo_generator/llm/prompts/endpoint_analysis.prompt
arazzo_generator/llm/prompts/user_workflow_instructions.prompt
arazzo_generator/parser/__init__.py
arazzo_generator/parser/openapi_parser.py
arazzo_generator/utils/__init__.py
arazzo_generator/utils/config.py
arazzo_generator/utils/exceptions.py
arazzo_generator/utils/logging.py
arazzo_generator/utils/serializer.py
arazzo_generator/utils/utils.py
arazzo_generator/utils/yaml_utils.py
arazzo_generator/validator/__init__.py
arazzo_generator/validator/arazzo_schema/1.0.1/arazzo-schema.yaml
arazzo_generator/validator/arazzo_validator.py
arazzo_generator-0.2.1.dist-info/RECORD
