Metadata-Version: 2.4
Name: arazzo_generator
Version: 0.2.1
Summary: Tool for analyzing OpenAPI specifications and generating meaningful Arazzo workflows by identifying logical API sequences and patterns.
Author-Email: Jentic <hello@jentic.com>
License-Expression: Apache-2.0
License-File: LICENSE
License-File: NOTICE
Project-URL: Homepage, https://github.com/jentic/arazzo-engine
Project-URL: Documentation, https://github.com/jentic/arazzo-engine#readme
Project-URL: Issues, https://github.com/jentic/arazzo-engine/issues
Requires-Python: <4.0,>=3.11
Requires-Dist: requests>=2.25.0
Requires-Dist: openapi-spec-validator>=0.5.0
Requires-Dist: prance>=0.22.0
Requires-Dist: click>=8.0.0
Requires-Dist: jsonschema>=4.0.0
Requires-Dist: Levenshtein~=0.27.1
Requires-Dist: fastapi>=0.95.0
Requires-Dist: uvicorn>=0.22.0
Requires-Dist: pydantic>=2.0.0
Requires-Dist: pyyaml>=6.0
Requires-Dist: litellm>=1.0.0
Requires-Dist: python-dotenv>=1.1.1
